minimizer.py
python_minimizer-2.0.1.dist-info/LICENSE.txt
python_minimizer-2.0.1.dist-info/METADATA
python_minimizer-2.0.1.dist-info/WHEEL
python_minimizer-2.0.1.dist-info/entry_points.txt
python_minimizer-2.0.1.dist-info/top_level.txt
python_minimizer-2.0.1.dist-info/RECORD
