Metadata-Version: 2.1
Name: python-minimizer
Version: 2.0.1
Summary: Minimizes Python code using Python's lexical scanning tokenize module.
Home-page: https://github.com/agroden/python-minimizer
Author: Alexander Groden
Author-email: alexander.groden@gmail.com
License: UNKNOWN
Keywords: minimization minification minimize minify mit-license
Platform: UNKNOWN
Classifier: Development Status :: 5 - Production/Stable
Classifier: Intended Audience :: Developers
Classifier: Environment :: Console
Classifier: Topic :: Software Development :: Build Tools
Classifier: Topic :: Software Development :: Libraries :: Python Modules
Classifier: License :: OSI Approved :: MIT License
Classifier: Programming Language :: Python :: 3
Classifier: Programming Language :: Python :: 3.8
